halotools-0.8.2.data/scripts/download_additional_halocat.py
halotools-0.8.2.data/scripts/rebuild_ptcl_table_cache_log.py
halotools-0.8.2.data/scripts/rebuild_halo_table_cache_log.py
halotools-0.8.2.data/scripts/download_initial_halocat.py
halotools-0.8.2.dist-info/WHEEL
halotools-0.8.2.dist-info/top_level.txt
halotools-0.8.2.dist-info/METADATA
halotools-0.8.2.dist-info/LICENSE.rst
halotools-0.8.2.dist-info/entry_points.txt
halotools-0.8.2.dist-info/RECORD
halotools.libs/libstdc++-a9383cce.so.6.0.28
halotools.libs/libgcc_s-a04fdf82.so.1
halotools/compiler_version.cpython-311-x86_64-linux-musl.so
halotools/_astropy_init.py
halotools/__init__.py
halotools/custom_exceptions.py
halotools/conftest.py
halotools/version.py
halotools/extern/__init__.py
halotools/utils/inverse_transformation_sampling.py
halotools/utils/rotations2d.py
halotools/utils/crossmatch.py
halotools/utils/group_member_generator.py
halotools/utils/array_indexing_manipulations.py
halotools/utils/__init__.py
halotools/utils/spherical_geometry.py
halotools/utils/mcrotations.py
halotools/utils/rotations3d.py
halotools/utils/distribution_matching.py
halotools/utils/io_utils.py
halotools/utils/probabilistic_binning.py
halotools/utils/python_string_comparisons.py
halotools/utils/table_utils.py
halotools/utils/value_added_halo_table_functions.py
halotools/utils/vector_utilities.py
halotools/utils/array_utils.py
halotools/utils/load_umachine_binaries.py
halotools/utils/conditional_percentile.py
halotools/utils/tests/test_value_added_halo_table_functions.py
halotools/utils/tests/setup_package.py
halotools/utils/tests/test_group_member_generator.py
halotools/utils/tests/__init__.py
halotools/utils/tests/test_table_utils.py
halotools/utils/tests/test_compute_richness.py
halotools/utils/tests/test_mcrotations.py
halotools/utils/tests/test_io_utils.py
halotools/utils/tests/test_distribution_matching.py
halotools/utils/tests/test_array_indexing_manipulations.py
halotools/utils/tests/test_python_string_comparisons.py
halotools/utils/tests/test_conditional_percentile.py
halotools/utils/tests/test_its.py
halotools/utils/tests/test_array_utils.py
