Metadata-Version: 2.1
Name: halotools
Version: 0.8.2
Summary: Package designed to analyze N-body simulations and constrain models of cosmology and galaxy evolution.
Home-page: http://astropy.org
Author: Andrew Hearin
Author-email: ahearin@anl.gov
License: BSD 3-Clause
Requires-Python: >=3.9
License-File: licenses/LICENSE.rst
Requires-Dist: astropy
Requires-Dist: numpy
Requires-Dist: scipy
Requires-Dist: requests
Requires-Dist: beautifulsoup4
Requires-Dist: cython
Provides-Extra: all
Requires-Dist: h5py ; extra == 'all'
Provides-Extra: docs
Requires-Dist: sphinx-astropy ; extra == 'docs'
Provides-Extra: test
Requires-Dist: pytest-astropy ; extra == 'test'
Requires-Dist: h5py ; extra == 'test'
